excel_anonymizer.py
excel_anonymizer-1.1.8.dist-info/LICENSE
excel_anonymizer-1.1.8.dist-info/METADATA
excel_anonymizer-1.1.8.dist-info/WHEEL
excel_anonymizer-1.1.8.dist-info/entry_points.txt
excel_anonymizer-1.1.8.dist-info/top_level.txt
excel_anonymizer-1.1.8.dist-info/RECORD
