Metadata-Version: 2.1
Name: excel_anonymizer
Version: 1.1.8
Summary: Anonymizes an Excel file and synthesizes new data in its place
Author: Siddharth Bhatia
Classifier: Development Status :: 5 - Production/Stable
Classifier: Environment :: Console
Classifier: Intended Audience :: Developers
Classifier: Intended Audience :: Education
Classifier: Intended Audience :: End Users/Desktop
Classifier: Intended Audience :: Information Technology
Classifier: License :: OSI Approved :: MIT License
Classifier: Operating System :: OS Independent
Classifier: Operating System :: Unix
Classifier: Operating System :: POSIX :: Linux
Classifier: Operating System :: MacOS :: MacOS X
Classifier: Operating System :: Microsoft :: Windows
Classifier: Programming Language :: Python
Classifier: Programming Language :: Python :: 3
Classifier: Programming Language :: Python :: 3 :: Only
Classifier: Programming Language :: Python :: 3.8
Classifier: Programming Language :: Python :: 3.9
Classifier: Programming Language :: Python :: 3.10
Classifier: Programming Language :: Python :: 3.11
Classifier: Topic :: Office/Business
Classifier: Topic :: Utilities
Classifier: Topic :: Office/Business :: Financial :: Spreadsheet
License-File: LICENSE
Requires-Dist: presidio-analyzer
Requires-Dist: presidio-anonymizer
Requires-Dist: pandas
Requires-Dist: pyarrow
Requires-Dist: faker
Requires-Dist: openpyxl
Requires-Dist: en-core-web-lg
